Workbook

Sheet Plan
A1: section | B1: item | C1: laptop scale (1M profiles) | D1: production target | E1: notes / source
A2: Targets | B2: RTO (restore the service from backup after loss of the cluster or logical corruption) | C2: 60 | D2: 30 | E2: Minutes. Budget for the laptop test: detect + decide 5, prepare empty target cluster 10, RESTORE <= 30, validation 10, cutover 5 = 60. Production: restore of the hot set is parallelised across nodes; target 30 min assumes the production dataset is restored by a cluster at least as large as the source (measure and re-plan; extrapolate with the B74 growth model).
A3: Targets | B3: RPO (maximum acceptable data loss, minutes) | C3: 15 | D3: 5 | E3: Minutes. RPO of a backup-based recovery = age of the newest completed incremental at the failure instant; with revision_history the restore can target any time up to that point (PITR). Node/zone/region failure is NOT a backup case: the 3-replica cluster survives it with RPO 0 (survival goal ZONE or REGION).
A4: Targets | B4: Backup window | C4: 15-minute incrementals, daily full | D4: 5-minute incrementals, daily full, weekly full copied to a second bucket/account | E4: CockroachDB schedules: incrementals recur on the cron given in RECURRING, full on FULL BACKUP clause.
A5: Targets | B5: Retention of backups | C5: 7 days incrementals, 4 fulls (laptop: disk permitting) | D5: 35 days PITR window (gc.ttlseconds not required for backup PITR), 13 monthly fulls (legal hold on audit/ledger evidence: 7 years via archive bucket with object lock) | E5: Align with data_retention_policy; erased subjects reappear in older backups: expire backups within 35 days or maintain an erasure re-apply list after a restore (DSR re-run job).
A6: Targets | B6: Restore test cadence | C6: Once before Gate 2 (B80), then each schema release | D6: Monthly full restore drill into the backup cluster; quarterly game-day with cutover rehearsal | E6: Record every run in sheet Log.
A7: Scale | B7: Dataset (laptop seed) | C7: 1,000,000 candidate profiles, 100,000 job requirements, 5,000,000 applications (docket section 6) | D7: 10M profiles / 1M requirements / 100M applications (extrapolation target, not loaded) | E7: Physical size is measured at run time and written to the Log (GB). Planning assumption: replication factor 3 means the logical (backed-up) size is about one third of cluster disk use.
A8: Method | B8: Backup type: full | C8: BACKUP INTO | D8: same | E8: Collection layout: each full creates a dated subdirectory under the collection URI; incrementals are appended to the latest full.
A9: Method | B9: Backup type: incremental | C9: BACKUP INTO LATEST IN | D9: same | E9: Chain length bounded by the daily full.
A10: Method | B10: Backup type: point-in-time (PITR) | C10: WITH revision_history on every full and incremental; RESTORE ... AS OF SYSTEM TIME | D10: same | E10: revision_history is on by default for scheduled backups (crdb_capabilities row 19) but the explicit option is kept for clarity.
A11: Method | B11: Backup location | C11: S3-compatible MinIO container on the host or an S3 bucket (external connection backup_store). nodelocal://1/... for a quick laptop run. | D11: S3/GCS/Azure bucket in a different account/region than the cluster, object lock on the archive bucket, server-side KMS plus client KMS option | E11: crdb_capabilities: S3, GCS, Azure are the tested stores; MinIO-style S3 is 'untested' per the docs; nodelocal as a backup target is not described on the fetched pages (unverified): smoke-test it first.
A12: Method | B12: Encryption of backups | C12: WITH encryption_passphrase (laptop) or KMS | D12: WITH kms = 'aws:///<key-arn>?AUTH=implicit&REGION=<r>' (or gcp:///...); separate key from the data-at-rest key; key policy allows backup_operator only | E12: Encrypted backups cannot use WITH EXPERIMENTAL COPY (Preview in v26.2, needs backup.compaction.threshold). Backup encryption options are from the official BACKUP docs, not from crdb_capabilities.md: verify on the pinned image. Application-encrypted columns (AES-GCM) stay ciphertext in every backup.
A13: Method | B13: Licence note | C13: Multi-node cluster needs a Free/Trial/Enterprise licence (throttle: 5 open txns after 7 days without one). RESTORE no longer requires Enterprise. Whether BACKUP (and encrypted/KMS backups, schedules, revision_history) are licence-gated is UNVERIFIED on the fetched pages. | D13: Enterprise licence (Enterprise Free if the revenue test is met) applied after cockroach init; full-cluster backups carry the licence key | E13: Source: crdb_capabilities sections 1 row 19 and 3.
A14: Method | B14: Separate backup cluster | C14: Second single-node (or 3-node) cluster started from the same image; used as restore target; no application connects to it | D14: Dedicated cluster in another region/account with its own CA; promoted only by the DR runbook | E14: infra/backup-db in the repository is the intended target; this sheet only documents the procedure.
A15: Method | B15: What is backed up | C15: BACKUP INTO (cluster) for the DR drill; BACKUP DATABASE talentra for the dataset test | D15: cluster backup nightly + database/table-level on demand | E15: Roles/users live in system tables: restore them with RESTORE SYSTEM USERS (verify) or recreate with the Grants script; table privileges travel with the descriptors.
... A17: Security | B17: Backup content sensitivity | C17: Contains all ciphertext, hashes and Personal data in clear (columns not app-encrypted) | D17: same | E17: Backups are as sensitive as the database: encrypted, access logged, retention-limited, restore only on the backup cluster, no copy to laptops after the drill.
B19: Summary of logged runs (reads sheet Log)
B20: Runs logged | C20: =COUNTA(Log!A2:A200)
B21: Runs with RTO met = Yes | C21: =COUNTIF(Log!P2:P200,"Yes")
B22: Runs with RTO met = No | C22: =COUNTIF(Log!P2:P200,"No")
B23: Longest restore (minutes) | C23: =IF(COUNT(Log!M2:M200)=0,"",MAX(Log!M2:M200))
B24: Longest backup (minutes) | C24: =IF(COUNT(Log!J2:J200)=0,"",MAX(Log!J2:J200))
B25: Worst RPO achieved (minutes) | C25: =IF(COUNT(Log!S2:S200)=0,"",MAX(Log!S2:S200))
B27: Include validation time in RTO? (Yes/No) | C27: Yes

Sheet Procedure
A1: step | B1: phase | C1: action | D1: SQL / command | E1: expected result | F1: role | G1: notes
A2: P-01 | B2: Preflight | C2: Record cluster version, node count, licence state, dataset counts. | D2: SELECT version(); SHOW CLUSTER SETTING enterprise.license; SELECT count(*) FROM candidate_profile; SELECT count(*) FROM job_requirement; SELECT count(*) FROM job_application; | E2: Counts match the seed plan (1M / 100k / 5M). Write them into Log notes. | F2: operator
A3: P-02 | B3: Preflight | C3: Create the storage location (external connection). | D3: CREATE EXTERNAL CONNECTION backup_store AS 's3://talentra-backups/laptop?AUTH=implicit'; -- MinIO: add &AWS_ENDPOINT=http://minio:9000 (credentials per AUTH mode); quick test: 'nodelocal://1/backups' | E3: SHOW EXTERNAL CONNECTIONS lists backup_store. | F3: backup_operator | G3: Smoke-test write access with a tiny BACKUP of one lookup table.
A4: P-03 | B4: Preflight | C4: Create the schedule (production pattern; for the drill run P-04..P-05 manually). | D4: CREATE SCHEDULE talentra_backup FOR BACKUP INTO 'external://backup_store' WITH revision_history, encryption_passphrase = '<from vault>' RECURRING '*/15 * * * *' FULL BACKUP '@daily' WITH SCHEDULE OPTIONS first_run = 'now', on_previous_running = 'wait'; | E4: SHOW SCHEDULES shows one full + one incremental schedule. | F4: backup_operator | G4: Replace the passphrase by kms = 'aws:///<arn>?AUTH=implicit&REGION=<r>' in production. Exact option names verified against the BACKUP / CREATE SCHEDULE docs on the pinned image.
A5: P-04 | B5: Backup | C5: Take a FULL backup of the seeded database and record start/end. | D5: BACKUP DATABASE talentra INTO 'external://backup_store' AS OF SYSTEM TIME '-10s' WITH revision_history, encryption_passphrase = '<from vault>'; | E5: Job succeeds; note job id. Backup duration = finished - started. | F5: backup_operator | G5: Cluster form for DR: BACKUP INTO 'external://backup_store' AS OF SYSTEM TIME '-10s' WITH revision_history;
A6: P-05 | B6: Backup | C6: Read the timing and size from the job record. | D6: SELECT job_id, job_type, status, created, started, finished, finished - started AS duration, fraction_completed FROM [SHOW JOBS] WHERE job_type = 'BACKUP' ORDER BY created DESC LIMIT 5; SHOW BACKUPS IN 'external://backup_store'; SHOW BACKUP FROM LATEST IN 'external://backup_store' WITH encryption_passphrase = '<from vault>'; | E6: Fill Log: backup start/end, size (GB) from SHOW BACKUP (size_bytes). | F6: operator
A7: P-06 | B7: Backup | C7: Generate change traffic (insert 10k applications, 5k ledger rows) then take an INCREMENTAL backup; remember the wall-clock time T_fail (simulated failure instant). | D7: BACKUP DATABASE talentra INTO LATEST IN 'external://backup_store' AS OF SYSTEM TIME '-10s' WITH revision_history, encryption_passphrase = '<from vault>'; | E7: Incremental finishes quickly; record end time; continue writing for a few minutes, then note T_fail = now(). | F7: backup_operator | G7: RPO achieved = T_fail - (AS OF time of the newest backup).
A8: P-07 | B8: Restore | C8: Prepare the target (separate backup cluster): empty cluster, same major version, same licence; connect as admin. | D8: SELECT version(); SHOW DATABASES; -- talentra must not exist (or use RESTORE ... WITH new_db_name = 'talentra_restore') | E8: Target is empty. | F8: backup_operator | G8: Never restore into the production cluster for a drill.
A9: P-08 | B9: Restore | C9: RESTORE the database; record start/end. | D9: RESTORE DATABASE talentra FROM LATEST IN 'external://backup_store' WITH encryption_passphrase = '<from vault>'; -- PITR: ... FROM LATEST IN '...' AS OF SYSTEM TIME '<timestamp inside revision history>'; | E9: Job succeeds; restore duration = finished - started. Single table drill: RESTORE TABLE talentra.public.wallet FROM LATEST IN '...' WITH into_db = 'talentra_restore'; | F9: backup_operator | G9: RESTORE no longer requires an Enterprise licence (crdb_capabilities).
A10: P-09 | B10: Restore | C10: Read restore timing. | D10: SELECT job_id, job_type, status, created, started, finished, finished - started AS duration FROM [SHOW JOBS] WHERE job_type = 'RESTORE' ORDER BY created DESC LIMIT 5; | E10: Fill Log: restore start/end, duration. | F10: operator
A11: P-10 | B11: Restore | C11: Recreate roles and grants (login secrets are not part of table backups). | D11: RESTORE SYSTEM USERS FROM LATEST IN 'external://backup_store' WITH encryption_passphrase = '<from vault>'; -- verify availability; otherwise run the Grants script of 13_rbac_matrix.xlsx (GR-01..GR-05) | E11: SHOW ROLES lists the same roles as the source; SHOW GRANTS matches (AT-45). | F11: backup_operator | G11: Do not restore production service passwords/certificates to the drill cluster; issue new certificates.
A12: P-11 | B12: Validate | C12: Run every check of sheet Validation against source (AS OF SYSTEM TIME = backup time) and restored cluster; compare output. | D12: See sheet Validation (V-01..). | E12: All checks equal; hash-chain verifiers pass. | F12: operator | G12: Record result in Log: Pass / Pass with notes / Fail.
A13: P-12 | B13: Validate | C13: Application smoke test on the restored cluster: login, search, apply, wallet debit with the standard test accounts. | D13: Run the B65 query set subset (3 queries) and one write transaction in a rolled-back txn. | E13: Queries return expected counts; writes succeed. | F13: operator | G13: Counts toward RTO only if the target was ready (P-07).
A14: P-13 | B14: Record | C14: Compute RTO met and RPO achieved (formulas in Log) and write the run in the Log; attach job ids and the Validation output. | D14: n/a | E14: RTO met = Yes when restore duration (+ validation duration when 'include validation' is ticked in Plan) <= RTO target. | F14: operator
A15: P-14 | B15: Clean up | C15: Drop the restored database or destroy the drill cluster; revoke the temporary credentials; keep backups per retention. | D15: DROP DATABASE talentra CASCADE; -- drill cluster only | E15: Target cluster empty; no drill data copied elsewhere. | F15: backup_operator

Sheet Log
A1: run_id | B1: date | C1: environment | D1: dataset rows (total) | E1: dataset size GB (logical, from SHOW BACKUP) | F1: backup type | G1: backup start | H1: backup end | I1: backup size GB | J1: backup duration (min) | K1: restore start | L1: restore end | M1: restore duration (min) | N1: validation duration (min) | O1: RTO target (min) | P1: RTO met | Q1: simulated failure time | R1: restored-to (AS OF) time | S1: RPO achieved (min) | T1: RPO target (min) | U1: RPO met | V1: validation result | W1: operator | X1: notes
J2: =IF(AND(ISNUMBER(G2),ISNUMBER(H2)),ROUND((H2-G2)*1440,2),"") | M2: =IF(AND(ISNUMBER(K2),ISNUMBER(L2)),ROUND((L2-K2)*1440,2),"") | O2: =IF(A2="","",Plan!$C$2) | P2: =IF(OR(M2="",O2=""),"",IF(M2+IF(Plan!$C$27="Yes",N2,0)<=O2,"Yes","No")) | S2: =IF(AND(ISNUMBER(Q2),ISNUMBER(R2)),ROUND((Q2-R2)*1440,2),"") | T2: =IF(A2="","",Plan!$C$3) | U2: =IF(OR(S2="",T2=""),"",IF(S2<=T2,"Yes","No"))
J3: =IF(AND(ISNUMBER(G3),ISNUMBER(H3)),ROUND((H3-G3)*1440,2),"") | M3: =IF(AND(ISNUMBER(K3),ISNUMBER(L3)),ROUND((L3-K3)*1440,2),"") | O3: =IF(A3="","",Plan!$C$2) | P3: =IF(OR(M3="",O3=""),"",IF(M3+IF(Plan!$C$27="Yes",N3,0)<=O3,"Yes","No")) | S3: =IF(AND(ISNUMBER(Q3),ISNUMBER(R3)),ROUND((Q3-R3)*1440,2),"") | T3: =IF(A3="","",Plan!$C$3) | U3: =IF(OR(S3="",T3=""),"",IF(S3<=T3,"Yes","No"))
J4: =IF(AND(ISNUMBER(G4),ISNUMBER(H4)),ROUND((H4-G4)*1440,2),"") | M4: =IF(AND(ISNUMBER(K4),ISNUMBER(L4)),ROUND((L4-K4)*1440,2),"") | O4: =IF(A4="","",Plan!$C$2) | P4: =IF(OR(M4="",O4=""),"",IF(M4+IF(Plan!$C$27="Yes",N4,0)<=O4,"Yes","No")) | S4: =IF(AND(ISNUMBER(Q4),ISNUMBER(R4)),ROUND((Q4-R4)*1440,2),"") | T4: =IF(A4="","",Plan!$C$3) | U4: =IF(OR(S4="",T4=""),"",IF(S4<=T4,"Yes","No"))
J5: =IF(AND(ISNUMBER(G5),ISNUMBER(H5)),ROUND((H5-G5)*1440,2),"") | M5: =IF(AND(ISNUMBER(K5),ISNUMBER(L5)),ROUND((L5-K5)*1440,2),"") | O5: =IF(A5="","",Plan!$C$2) | P5: =IF(OR(M5="",O5=""),"",IF(M5+IF(Plan!$C$27="Yes",N5,0)<=O5,"Yes","No")) | S5: =IF(AND(ISNUMBER(Q5),ISNUMBER(R5)),ROUND((Q5-R5)*1440,2),"") | T5: =IF(A5="","",Plan!$C$3) | U5: =IF(OR(S5="",T5=""),"",IF(S5<=T5,"Yes","No"))
J6: =IF(AND(ISNUMBER(G6),ISNUMBER(H6)),ROUND((H6-G6)*1440,2),"") | M6: =IF(AND(ISNUMBER(K6),ISNUMBER(L6)),ROUND((L6-K6)*1440,2),"") | O6: =IF(A6="","",Plan!$C$2) | P6: =IF(OR(M6="",O6=""),"",IF(M6+IF(Plan!$C$27="Yes",N6,0)<=O6,"Yes","No")) | S6: =IF(AND(ISNUMBER(Q6),ISNUMBER(R6)),ROUND((Q6-R6)*1440,2),"") | T6: =IF(A6="","",Plan!$C$3) | U6: =IF(OR(S6="",T6=""),"",IF(S6<=T6,"Yes","No"))
J7: =IF(AND(ISNUMBER(G7),ISNUMBER(H7)),ROUND((H7-G7)*1440,2),"") | M7: =IF(AND(ISNUMBER(K7),ISNUMBER(L7)),ROUND((L7-K7)*1440,2),"") | O7: =IF(A7="","",Plan!$C$2) | P7: =IF(OR(M7="",O7=""),"",IF(M7+IF(Plan!$C$27="Yes",N7,0)<=O7,"Yes","No")) | S7: =IF(AND(ISNUMBER(Q7),ISNUMBER(R7)),ROUND((Q7-R7)*1440,2),"") | T7: =IF(A7="","",Plan!$C$3) | U7: =IF(OR(S7="",T7=""),"",IF(S7<=T7,"Yes","No"))
J8: =IF(AND(ISNUMBER(G8),ISNUMBER(H8)),ROUND((H8-G8)*1440,2),"") | M8: =IF(AND(ISNUMBER(K8),ISNUMBER(L8)),ROUND((L8-K8)*1440,2),"") | O8: =IF(A8="","",Plan!$C$2) | P8: =IF(OR(M8="",O8=""),"",IF(M8+IF(Plan!$C$27="Yes",N8,0)<=O8,"Yes","No")) | S8: =IF(AND(ISNUMBER(Q8),ISNUMBER(R8)),ROUND((Q8-R8)*1440,2),"") | T8: =IF(A8="","",Plan!$C$3) | U8: =IF(OR(S8="",T8=""),"",IF(S8<=T8,"Yes","No"))
J9: =IF(AND(ISNUMBER(G9),ISNUMBER(H9)),ROUND((H9-G9)*1440,2),"") | M9: =IF(AND(ISNUMBER(K9),ISNUMBER(L9)),ROUND((L9-K9)*1440,2),"") | O9: =IF(A9="","",Plan!$C$2) | P9: =IF(OR(M9="",O9=""),"",IF(M9+IF(Plan!$C$27="Yes",N9,0)<=O9,"Yes","No")) | S9: =IF(AND(ISNUMBER(Q9),ISNUMBER(R9)),ROUND((Q9-R9)*1440,2),"") | T9: =IF(A9="","",Plan!$C$3) | U9: =IF(OR(S9="",T9=""),"",IF(S9<=T9,"Yes","No"))
J10: =IF(AND(ISNUMBER(G10),ISNUMBER(H10)),ROUND((H10-G10)*1440,2),"") | M10: =IF(AND(ISNUMBER(K10),ISNUMBER(L10)),ROUND((L10-K10)*1440,2),"") | O10: =IF(A10="","",Plan!$C$2) | P10: =IF(OR(M10="",O10=""),"",IF(M10+IF(Plan!$C$27="Yes",N10,0)<=O10,"Yes","No")) | S10: =IF(AND(ISNUMBER(Q10),ISNUMBER(R10)),ROUND((Q10-R10)*1440,2),"") | T10: =IF(A10="","",Plan!$C$3) | U10: =IF(OR(S10="",T10=""),"",IF(S10<=T10,"Yes","No"))
J11: =IF(AND(ISNUMBER(G11),ISNUMBER(H11)),ROUND((H11-G11)*1440,2),"") | M11: =IF(AND(ISNUMBER(K11),ISNUMBER(L11)),ROUND((L11-K11)*1440,2),"") | O11: =IF(A11="","",Plan!$C$2) | P11: =IF(OR(M11="",O11=""),"",IF(M11+IF(Plan!$C$27="Yes",N11,0)<=O11,"Yes","No")) | S11: =IF(AND(ISNUMBER(Q11),ISNUMBER(R11)),ROUND((Q11-R11)*1440,2),"") | T11: =IF(A11="","",Plan!$C$3) | U11: =IF(OR(S11="",T11=""),"",IF(S11<=T11,"Yes","No"))
J12: =IF(AND(ISNUMBER(G12),ISNUMBER(H12)),ROUND((H12-G12)*1440,2),"") | M12: =IF(AND(ISNUMBER(K12),ISNUMBER(L12)),ROUND((L12-K12)*1440,2),"") | O12: =IF(A12="","",Plan!$C$2) | P12: =IF(OR(M12="",O12=""),"",IF(M12+IF(Plan!$C$27="Yes",N12,0)<=O12,"Yes","No")) | S12: =IF(AND(ISNUMBER(Q12),ISNUMBER(R12)),ROUND((Q12-R12)*1440,2),"") | T12: =IF(A12="","",Plan!$C$3) | U12: =IF(OR(S12="",T12=""),"",IF(S12<=T12,"Yes","No"))
J13: =IF(AND(ISNUMBER(G13),ISNUMBER(H13)),ROUND((H13-G13)*1440,2),"") | M13: =IF(AND(ISNUMBER(K13),ISNUMBER(L13)),ROUND((L13-K13)*1440,2),"") | O13: =IF(A13="","",Plan!$C$2) | P13: =IF(OR(M13="",O13=""),"",IF(M13+IF(Plan!$C$27="Yes",N13,0)<=O13,"Yes","No")) | S13: =IF(AND(ISNUMBER(Q13),ISNUMBER(R13)),ROUND((Q13-R13)*1440,2),"") | T13: =IF(A13="","",Plan!$C$3) | U13: =IF(OR(S13="",T13=""),"",IF(S13<=T13,"Yes","No"))
... J61: =IF(AND(ISNUMBER(G61),ISNUMBER(H61)),ROUND((H61-G61)*1440,2),"") | M61: =IF(AND(ISNUMBER(K61),ISNUMBER(L61)),ROUND((L61-K61)*1440,2),"") | O61: =IF(A61="","",Plan!$C$2) | P61: =IF(OR(M61="",O61=""),"",IF(M61+IF(Plan!$C$27="Yes",N61,0)<=O61,"Yes","No")) | S61: =IF(AND(ISNUMBER(Q61),ISNUMBER(R61)),ROUND((Q61-R61)*1440,2),"") | T61: =IF(A61="","",Plan!$C$3) | U61: =IF(OR(S61="",T61=""),"",IF(S61<=T61,"Yes","No"))

Sheet Validation
A1: id | B1: type | C1: check | D1: SQL / action | E1: expected | F1: severity
A2: V-01 | B2: Schema | C2: Table count identical | D2: SELECT count(*) FROM information_schema.tables WHERE table_schema = 'public' AND table_type = 'BASE TABLE'; | E2: =source (1306 tables in the model) | F2: High
A3: V-02 | B3: Schema | C3: View count identical | D3: SELECT count(*) FROM information_schema.views WHERE table_schema = 'public'; | E3: =source | F3: High
A4: V-03 | B4: Schema | C4: Constraint inventory identical | D4: SELECT constraint_type, count(*) FROM information_schema.table_constraints WHERE table_schema = 'public' GROUP BY 1 ORDER BY 1; | E4: =source for every type | F4: High
A5: V-04 | B5: Schema | C5: Index inventory identical | D5: SELECT count(*) FROM information_schema.statistics WHERE table_schema = 'public'; | E5: =source | F5: Medium
A6: V-05 | B6: Schema | C6: Foreign keys valid | D6: SELECT conname, conrelid::REGCLASS FROM pg_catalog.pg_constraint WHERE contype = 'f' AND NOT convalidated; | E6: 0 rows | F6: High
A7: V-06 | B7: Security | C7: Roles identical | D7: SELECT username, member_of FROM [SHOW USERS] ORDER BY 1; | E7: =source minus drill-excluded logins | F7: High
A8: V-07 | B8: Security | C8: Grants identical on audit/ledger tables | D8: SHOW GRANTS ON TABLE audit_event, wallet_ledger_entry, profile_download, login_attempt; | E8: no UPDATE/DELETE for any grantee (13_rbac_matrix, AT-09) | F8: High
A9: V-08 | B9: Security | C9: No grants for PUBLIC on data tables | D9: SELECT table_name, privilege_type FROM information_schema.table_privileges WHERE grantee = 'public' AND table_schema = 'public'; | E9: 0 rows | F9: High
A10: V-09 | B10: Row count + checksum | C10: app_user: count and id checksum equal to source at the backup time | D10: SELECT count(*) AS n, sum(crc32c(id::STRING)) AS chk FROM app_user; -- source: add AS OF SYSTEM TIME '<backup AS OF time>' | E10: n and chk equal | F10: High
A11: V-10 | B11: Row count + checksum | C11: candidate_profile: count and id checksum equal to source at the backup time | D11: SELECT count(*) AS n, sum(crc32c(id::STRING)) AS chk FROM candidate_profile; -- source: add AS OF SYSTEM TIME '<backup AS OF time>' | E11: n and chk equal | F11: High
A12: V-11 | B12: Row count + checksum | C12: job_requirement: count and id checksum equal to source at the backup time | D12: SELECT count(*) AS n, sum(crc32c(id::STRING)) AS chk FROM job_requirement; -- source: add AS OF SYSTEM TIME '<backup AS OF time>' | E12: n and chk equal | F12: High
A13: V-12 | B13: Row count + checksum | C13: job_application: count and id checksum equal to source at the backup time | D13: SELECT count(*) AS n, sum(crc32c(id::STRING)) AS chk FROM job_application; -- source: add AS OF SYSTEM TIME '<backup AS OF time>' | E13: n and chk equal | F13: High
A14: V-13 | B14: Row count + checksum | C14: organisation: count and id checksum equal to source at the backup time | D14: SELECT count(*) AS n, sum(crc32c(id::STRING)) AS chk FROM organisation; -- source: add AS OF SYSTEM TIME '<backup AS OF time>' | E14: n and chk equal | F14: High
A15: V-14 | B15: Row count + checksum | C15: wallet: count and id checksum equal to source at the backup time | D15: SELECT count(*) AS n, sum(crc32c(id::STRING)) AS chk FROM wallet; -- source: add AS OF SYSTEM TIME '<backup AS OF time>' | E15: n and chk equal | F15: High
A16: V-15 | B16: Row count + checksum | C16: wallet_ledger_entry: count and id checksum equal to source at the backup time | D16: SELECT count(*) AS n, sum(crc32c(id::STRING)) AS chk FROM wallet_ledger_entry; -- source: add AS OF SYSTEM TIME '<backup AS OF time>' | E16: n and chk equal | F16: High
A17: V-16 | B17: Row count + checksum | C17: payment_order: count and id checksum equal to source at the backup time | D17: SELECT count(*) AS n, sum(crc32c(id::STRING)) AS chk FROM payment_order; -- source: add AS OF SYSTEM TIME '<backup AS OF time>' | E17: n and chk equal | F17: High
A18: V-17 | B18: Row count + checksum | C18: profile_download: count and id checksum equal to source at the backup time | D18: SELECT count(*) AS n, sum(crc32c(id::STRING)) AS chk FROM profile_download; -- source: add AS OF SYSTEM TIME '<backup AS OF time>' | E18: n and chk equal | F18: High
A19: V-18 | B19: Row count + checksum | C19: audit_event: count and id checksum equal to source at the backup time | D19: SELECT count(*) AS n, sum(crc32c(id::STRING)) AS chk FROM audit_event; -- source: add AS OF SYSTEM TIME '<backup AS OF time>' | E19: n and chk equal | F19: High
... A49: V-48 | B49: Row count + checksum | C49: fact_wallet_transaction: count and id checksum equal to source at the backup time | D49: SELECT count(*) AS n, sum(crc32c(id::STRING)) AS chk FROM fact_wallet_transaction; -- source: add AS OF SYSTEM TIME '<backup AS OF time>' | E49: n and chk equal | F49: Medium
A50: V-49 | B50: Row count | C50: Lookup tables: total rows over all lookups | D50: SELECT sum(n) FROM (SELECT count(*) AS n FROM actor_type UNION ALL SELECT count(*) AS n FROM user_status UNION ALL SELECT count(*) AS n FROM erasure_state UNION ALL SELECT count(*) AS n FROM registration_channel UNION ALL SELECT count(*) AS n FROM consent_source UNION ALL SELECT count(*) AS n FROM consent_action UNION ALL SELECT count(*) AS n FROM consent_type UNION ALL SELECT count(*) AS n FROM audit_action UNION ALL SELECT count(*) AS n FROM audit_entity_type UNION ALL SELECT count(*) AS n FROM audit_outcome UNION ALL SELECT count(*) AS n FROM enforcement_layer UNION ALL SELECT count(*) AS n FROM permission_operation UNION ALL SELECT count(*) AS n FROM data_scope UNION ALL SELECT count(*) AS n FROM hash_algorithm UNION ALL SELECT count(*) AS n FROM credential_change_reason UNION ALL SELECT count(*) AS n FROM credential_event_type UNION ALL SELECT count(*) AS n FROM mfa_method UNION ALL SELECT count(*) AS n FROM email_verification_purpose UNION ALL SELECT count(*) AS n FROM auth_method UNION ALL SELECT count(*) AS n FROM session_revoke_reason UNION ALL SELECT count(*) AS n FROM block_direction UNION ALL SELECT count(*) AS n FROM event_severity UNION ALL SELECT count(*) AS n FROM error_code UNION ALL SELECT count(*) AS n FROM approval_status UNION ALL SELECT count(*) AS n FROM duplicate_match_rule UNION ALL SELECT count(*) AS n FROM duplicate_match_status UNION ALL SELECT count(*) AS n FROM dsr_type UNION ALL SELECT count(*) AS n FROM dsr_status UNION ALL SELECT count(*) AS n FROM request_channel UNION ALL SELECT count(*) AS n FROM retention_action UNION ALL SELECT count(*) AS n FROM retention_trigger UNION ALL SELECT count(*) AS n FROM job_run_status UNION ALL SELECT count(*) AS n FROM ip_rule_kind UNION ALL SELECT count(*) AS n FROM api_client_kind UNION ALL SELECT count(*) AS n FROM impersonation_reason UNION ALL SELECT count(*) AS n FROM moderation_target_type UNION ALL SELECT count(*) AS n FROM moderation_reason UNION ALL SELECT count(*) AS n FROM moderation_case_status UNION ALL SELECT count(*) AS n FROM moderation_action UNION ALL SELECT count(*) AS n FROM security_event_type UNION ALL SELECT count(*) AS n FROM legacy_entity_kind UNION ALL SELECT count(*) AS n FROM legacy_conflict_outcome) s; | E50: =source (extend to all 536 lookups with a generated script) | F50: Low
A51: V-50 | B51: Integrity | C51: Wallet balances equal ledger | D51: SELECT * FROM vw_wallet_balance_drift LIMIT 10; | E51: 0 rows (BR-SUB-08) | F51: High
A52: V-51 | B52: Integrity | C52: Subscription periods do not overlap | D52: SELECT * FROM vw_subscription_period_overlap LIMIT 10; | E52: 0 rows (BR-SUB-03) | F52: High
A53: V-52 | B53: Integrity | C53: Invoice numbers gapless | D53: SELECT * FROM vw_invoice_number_gap LIMIT 10; | E53: 0 rows (BR-SUB-12) | F53: High
A54: V-53 | B54: Integrity | C54: Audit hash chains verify | D54: -- run the chain verifier job: for each chain_no recompute row_hash = SHA-256(fields || prev_hash) and compare; compare newest chain_seq per chain_no with audit_chain_head | E54: no mismatch; zero security_event(audit_chain_break) created (BR-ADM-09) | F54: High
A55: V-54 | B55: Integrity | C55: Wallet ledger chain verifies | D55: -- nightly verifier for wallet_ledger_entry (row_hash chain per wallet) restricted to wallets touched in the last 24 h plus a 1% random sample | E55: no mismatch (BR-SUB-10) | F55: High
A56: V-55 | B56: Integrity | C56: One live subscription per licence | D56: SELECT licence_id, count(*) FROM subscription WHERE ended_at IS NULL AND deleted_at IS NULL GROUP BY 1 HAVING count(*) > 1; | E56: 0 rows (BR-SUB-01) | F56: Medium
A57: V-56 | B57: Integrity | C57: Seat/device limits hold | D57: SELECT device_slot_id, count(*) FROM device_session WHERE ended_at IS NULL GROUP BY 1 HAVING count(*) > 1; | E57: 0 rows (BR-LIC-05) | F57: High
A58: V-57 | B58: Integrity | C58: Open recruiter mappings unique | D58: SELECT recruiter_app_user_id, organisation_id, count(*) FROM recruiter_organisation_mapping WHERE effective_to IS NULL GROUP BY 1, 2 HAVING count(*) > 1; | E58: 0 rows (BR-ORG-01) | F58: Medium
A59: V-58 | B59: Integrity | C59: Orphan check for deliberately FK-less references | D59: SELECT count(*) FROM audit_event a LEFT JOIN app_user u ON u.id = a.actor_app_user_id WHERE a.actor_app_user_id IS NOT NULL AND u.id IS NULL; | E59: 0 (or equal to source) | F59: Medium
A60: V-59 | B60: Integrity | C60: Blocked-party visibility still holds after restore | D60: SELECT count(*) FROM vw_candidate_visible_to_user WHERE viewer_app_user_id = '<blocked viewer>' AND candidate_app_user_id = '<blocker>'; | E60: 0 (AT-05) | F60: High
A61: V-60 | B61: Privacy | C61: Erased subjects are still erased | D61: SELECT count(*) FROM candidate_profile WHERE anonymised_at IS NOT NULL AND (contact_email IS NOT NULL OR contact_phone IS NOT NULL); | E61: 0; if > 0 re-run the erasure job from candidate_erasure_request (backups may predate erasure) | F61: High
A62: V-61 | B62: Privacy | C62: Legal holds preserved | D62: SELECT count(*) FROM legal_hold WHERE released_at IS NULL; | E62: =source | F62: Medium
A63: V-62 | B63: Time | C63: Timestamps in range (no clock-skew artefacts) | D63: SELECT max(created_at) FROM audit_event; SELECT max(created_at) FROM wallet_ledger_entry; | E63: <= backup AS OF time | F63: Medium
A64: V-63 | B64: Function | C64: Application smoke | D64: Run the three standard B65 queries and one wallet debit in a rolled-back txn | E64: same result shape and counts as source; debit succeeds | F64: High
